hdl_pi_if/backend.py
hdl_pi_if/pkginfo.py
hdl_pi_if/hdl_services.py
hdl_pi_if/__init__.py
hdl_pi_if/entry.cpython-312-x86_64-linux-gnu.so
hdl_pi_if/__build_num__.py
hdl_pi_if/vpi/__init__.py
hdl_pi_if/vpi/api.py
hdl_pi_if/impl/backend_cocotb.py
hdl_pi_if/impl/backend_asyncio.py
hdl_pi_if/dpi/hdl_services_dpi.py
hdl_pi_if/dpi/__init__.py
pyhdl_pi_if-0.0.1.8675558542.dist-info/top_level.txt
pyhdl_pi_if-0.0.1.8675558542.dist-info/METADATA
pyhdl_pi_if-0.0.1.8675558542.dist-info/WHEEL
pyhdl_pi_if-0.0.1.8675558542.dist-info/entry_points.txt
pyhdl_pi_if-0.0.1.8675558542.dist-info/RECORD
pyhdl_pi_if-0.0.1.8675558542.dist-info/LICENSE
